snaggr/__init__.py
snaggr/snaggr.py
snaggr-0.18.dist-info/LICENSE.txt
snaggr-0.18.dist-info/METADATA
snaggr-0.18.dist-info/WHEEL
snaggr-0.18.dist-info/top_level.txt
snaggr-0.18.dist-info/RECORD
